__init__.py
picta_common_layer.py
picta_image_model.py
picta_view.py
picta_view_model.py
picta_gui-1.0.1.dist-info/LICENSE
picta_gui-1.0.1.dist-info/METADATA
picta_gui-1.0.1.dist-info/WHEEL
picta_gui-1.0.1.dist-info/top_level.txt
picta_gui-1.0.1.dist-info/RECORD
