Metadata-Version: 2.1
Name: picta-gui
Version: 1.0.1
Summary: Simple GUI for use with identifying turtle plastrons
Author: Andrew Hanigan
Author-email: andrew.hanigan@intelligent-it.com
License: MIT
License-File: LICENSE
Requires-Dist: opencv-python
Requires-Dist: psd-tools
Requires-Dist: tensorflow ==2.13.0
Requires-Dist: Pillow
Requires-Dist: rawpy
